ophyd_basler/__init__.py
ophyd_basler/_version.py
ophyd_basler/basler_camera.py
ophyd_basler/basler_handler.py
ophyd_basler/custom_images.py
ophyd_basler/utils.py
ophyd_basler/tests/__init__.py
ophyd_basler/tests/conftest.py
ophyd_basler/tests/test_emulated_camera.py
ophyd_basler-0.2.3.dist-info/AUTHORS.rst
ophyd_basler-0.2.3.dist-info/LICENSE
ophyd_basler-0.2.3.dist-info/METADATA
ophyd_basler-0.2.3.dist-info/WHEEL
ophyd_basler-0.2.3.dist-info/top_level.txt
ophyd_basler-0.2.3.dist-info/RECORD
