Metadata-Version: 2.1
Name: ophyd-basler
Version: 0.2.3
Summary: Basler camera API integration with ophyd
Home-page: https://github.com/BNL-ATF/ophyd-basler
Author: Brookhaven National Lab
Author-email: tmorris@bnl.gov
License: BSD (3-clause)
Classifier: Development Status :: 2 - Pre-Alpha
Classifier: Natural Language :: English
Classifier: Programming Language :: Python :: 3
Requires-Python: >=3.8
License-File: LICENSE
License-File: AUTHORS.rst
Requires-Dist: area-detector-handlers
Requires-Dist: bluesky
Requires-Dist: databroker
Requires-Dist: event-model
Requires-Dist: h5py
Requires-Dist: ipython
Requires-Dist: matplotlib
Requires-Dist: napari[all]
Requires-Dist: numpy
Requires-Dist: opencv-python
Requires-Dist: ophyd
Requires-Dist: pypylon
